msdlib/__init__.py
msdlib/dataset.py
msdlib/msdExceptions.py
msdlib/msdbacktest.py
msdlib/scrap.py
msdlib/stats.py
msdlib/mlutils/__init__.py
msdlib/mlutils/modeling.py
msdlib/mlutils/utils.py
msdlib/msd/__init__.py
msdlib/msd/processing.py
msdlib/msd/vis.py
msdlib-1.1.16.dist-info/licenses/LICENSE
msdlib-1.1.16.dist-info/METADATA
msdlib-1.1.16.dist-info/WHEEL
msdlib-1.1.16.dist-info/top_level.txt
msdlib-1.1.16.dist-info/RECORD
