Metadata-Version: 2.4
Name: msdlib
Version: 1.1.16
Summary: msdlib is meant for making life easier of a common data scientist/data analyst/ML enginner.
Home-page: https://github.com/abdullah-al-masud/msdlib
Author: Abdullah Al Masud
Author-email: abdullahalmasud.buet@gmail.com
Classifier: Programming Language :: Python :: 3
Classifier: License :: OSI Approved :: MIT License
Classifier: Operating System :: OS Independent
Requires-Python: >=3.8
License-File: LICENSE
Requires-Dist: scipy
Requires-Dist: numpy
Requires-Dist: matplotlib
Requires-Dist: seaborn
Requires-Dist: pandas
Requires-Dist: joblib
Requires-Dist: tensorboard
Dynamic: author
Dynamic: author-email
Dynamic: classifier
Dynamic: description
Dynamic: description-content-type
Dynamic: home-page
Dynamic: license-file
Dynamic: requires-dist
Dynamic: requires-python
Dynamic: summary
